<?xml version="1.0" encoding="UTF-8"?>
<java version="1.8.0_101" class="java.beans.XMLDecoder">
 <object class="org.eclipse.epp.internal.mpc.ui.catalog.MarketplaceInfo" id="MarketplaceInfo0">
  <void property="iuToNodeKey">
   <void method="put">
    <string>org.jboss.tools.pde.sourcelookup.feature</string>
    <object class="java.util.ArrayList">
     <void method="add">
      <string>http://marketplace.eclipse.org#2844330</string>
     </void>
    </object>
   </void>
   <void method="put">
    <string>org.zeroturnaround.eclipse.feature</string>
    <object class="java.util.ArrayList">
     <void method="add">
      <string>http://marketplace.eclipse.org#29591</string>
     </void>
    </object>
   </void>
   <void method="put">
    <string>org.eclipse.pde</string>
    <object class="java.util.ArrayList">
     <void method="add">
      <string>http://marketplace.eclipse.org#2234530</string>
     </void>
    </object>
   </void>
   <void method="put">
    <string>com.remainsoftware.featureexplorer.feature</string>
    <object class="java.util.ArrayList">
     <void method="add">
      <string>http://marketplace.eclipse.org#22937</string>
     </void>
    </object>
   </void>
   <void method="put">
    <string>com.vaadin.designer.eclipse</string>
    <object class="java.util.ArrayList">
     <void method="add">
      <string>http://marketplace.eclipse.org#1023</string>
     </void>
    </object>
   </void>
   <void method="put">
    <string>com.vaadin.designer2.eclipse</string>
    <object class="java.util.ArrayList">
     <void method="add">
      <string>http://marketplace.eclipse.org#1023</string>
     </void>
    </object>
   </void>
   <void method="put">
    <string>org.eclipse.rcp.java8patch</string>
    <object class="java.util.ArrayList">
     <void method="add">
      <string>http://marketplace.eclipse.org#1392433</string>
     </void>
    </object>
   </void>
   <void method="put">
    <string>org.modelbus.teamprovider</string>
    <object class="java.util.ArrayList">
     <void method="add">
      <string>http://marketplace.eclipse.org#515053</string>
     </void>
    </object>
   </void>
   <void method="put">
    <string>com.teamunify.eclipse.mylyn.pivotaltracker</string>
    <object class="java.util.ArrayList">
     <void method="add">
      <string>http://marketplace.eclipse.org#28523</string>
     </void>
    </object>
   </void>
   <void method="put">
    <string>com.sap.core.tools.eclipse.server.feature</string>
    <object class="java.util.ArrayList">
     <void method="add">
      <string>http://marketplace.eclipse.org#3155121</string>
     </void>
    </object>
   </void>
   <void method="put">
    <string>com.so.eclipse.helper</string>
    <object class="java.util.ArrayList">
     <void method="add">
      <string>http://marketplace.eclipse.org#2563246</string>
     </void>
    </object>
   </void>
   <void method="put">
    <string>net.atos.webtools.tapestry</string>
    <object class="java.util.ArrayList">
     <void method="add">
      <string>http://marketplace.eclipse.org#1277887</string>
     </void>
    </object>
   </void>
   <void method="put">
    <string>org.modelbus.papyrus.eclipse.adapter</string>
    <object class="java.util.ArrayList">
     <void method="add">
      <string>http://marketplace.eclipse.org#515053</string>
     </void>
    </object>
   </void>
   <void method="put">
    <string>org.modelbus.papyrus.v9.eclipse.adapter</string>
    <object class="java.util.ArrayList">
     <void method="add">
      <string>http://marketplace.eclipse.org#515053</string>
     </void>
    </object>
   </void>
   <void method="put">
    <string>com.zeroc.IceBuilder</string>
    <object class="java.util.ArrayList">
     <void method="add">
      <string>http://marketplace.eclipse.org#2449032</string>
     </void>
    </object>
   </void>
   <void method="put">
    <string>uk.org.secondfiddle.pep.pde</string>
    <object class="java.util.ArrayList">
     <void method="add">
      <string>http://marketplace.eclipse.org#2117702</string>
     </void>
    </object>
   </void>
   <void method="put">
    <string>hu.textualmodeler.feature</string>
    <object class="java.util.ArrayList">
     <void method="add">
      <string>http://marketplace.eclipse.org#1504109</string>
     </void>
    </object>
   </void>
   <void method="put">
    <string>org.modelbus.teamprovider.emf.compare11.extension</string>
    <object class="java.util.ArrayList">
     <void method="add">
      <string>http://marketplace.eclipse.org#515053</string>
     </void>
    </object>
   </void>
   <void method="put">
    <string>uk.org.secondfiddle.pep.productivity</string>
    <object class="java.util.ArrayList">
     <void method="add">
      <string>http://marketplace.eclipse.org#2117702</string>
     </void>
    </object>
   </void>
   <void method="put">
    <string>org.zeroturnaround.eclipse.wtp.feature</string>
    <object class="java.util.ArrayList">
     <void method="add">
      <string>http://marketplace.eclipse.org#29591</string>
     </void>
    </object>
   </void>
   <void method="put">
    <string>com.reprezen.swagedit.feature</string>
    <object class="java.util.ArrayList">
     <void method="add">
      <string>http://marketplace.eclipse.org#3429028</string>
     </void>
    </object>
   </void>
   <void method="put">
    <string>com.sap.core.tools.eclipse.help.feature</string>
    <object class="java.util.ArrayList">
     <void method="add">
      <string>http://marketplace.eclipse.org#3155121</string>
     </void>
    </object>
   </void>
   <void method="put">
    <string>net.jeeeyul.pdetools.feature</string>
    <object class="java.util.ArrayList">
     <void method="add">
      <string>http://marketplace.eclipse.org#367947</string>
     </void>
    </object>
   </void>
   <void method="put">
    <string>org.modelbus.library.example</string>
    <object class="java.util.ArrayList">
     <void method="add">
      <string>http://marketplace.eclipse.org#515053</string>
     </void>
    </object>
   </void>
   <void method="put">
    <string>org.eclipse.jdt.java8patch</string>
    <object class="java.util.ArrayList">
     <void method="add">
      <string>http://marketplace.eclipse.org#1392433</string>
     </void>
    </object>
   </void>
   <void method="put">
    <string>de.jcup.jenkinseditor.feature</string>
    <object class="java.util.ArrayList">
     <void method="add">
      <string>http://marketplace.eclipse.org#3680354</string>
     </void>
    </object>
   </void>
   <void method="put">
    <string>org.modelbus.team.eclipse.ui.services</string>
    <object class="java.util.ArrayList">
     <void method="add">
      <string>http://marketplace.eclipse.org#515053</string>
     </void>
    </object>
   </void>
   <void method="put">
    <string>org.modelbus.team.eclipse.changemodelnotification</string>
    <object class="java.util.ArrayList">
     <void method="add">
      <string>http://marketplace.eclipse.org#515053</string>
     </void>
    </object>
   </void>
   <void method="put">
    <string>org.eclipse.pde.visualization.dependency_feature.feature.group</string>
    <object class="java.util.ArrayList">
     <void method="add">
      <string>http://marketplace.eclipse.org#1508744</string>
     </void>
    </object>
   </void>
   <void method="put">
    <string>uk.org.secondfiddle.pep</string>
    <object class="java.util.ArrayList">
     <void method="add">
      <string>http://marketplace.eclipse.org#2117702</string>
     </void>
    </object>
   </void>
   <void method="put">
    <string>org.modelbus.core</string>
    <object class="java.util.ArrayList">
     <void method="add">
      <string>http://marketplace.eclipse.org#515053</string>
     </void>
    </object>
   </void>
   <void method="put">
    <string>com.github.eclipse.projectlocationupdater.feature</string>
    <object class="java.util.ArrayList">
     <void method="add">
      <string>http://marketplace.eclipse.org#539811</string>
     </void>
    </object>
   </void>
   <void method="put">
    <string>net.jeeeyul.swtend.feature</string>
    <object class="java.util.ArrayList">
     <void method="add">
      <string>http://marketplace.eclipse.org#367947</string>
     </void>
    </object>
   </void>
   <void method="put">
    <string>org.cohorte.eclipse</string>
    <object class="java.util.ArrayList">
     <void method="add">
      <string>http://marketplace.eclipse.org#3035880</string>
     </void>
    </object>
   </void>
   <void method="put">
    <string>com.vaadin.integration.eclipse</string>
    <object class="java.util.ArrayList">
     <void method="add">
      <string>http://marketplace.eclipse.org#1023</string>
     </void>
    </object>
   </void>
   <void method="put">
    <string>io.sloeber.feature.feature.group</string>
    <object class="java.util.ArrayList">
     <void method="add">
      <string>http://marketplace.eclipse.org#1465503</string>
     </void>
     <void method="add">
      <string>http://marketplace.eclipse.org#2637354</string>
     </void>
    </object>
   </void>
   <void method="put">
    <string>org.zeroturnaround.eclipse.m2e.feature</string>
    <object class="java.util.ArrayList">
     <void method="add">
      <string>http://marketplace.eclipse.org#29591</string>
     </void>
    </object>
   </void>
   <void method="put">
    <string>org.eclipse.pde.java8patch</string>
    <object class="java.util.ArrayList">
     <void method="add">
      <string>http://marketplace.eclipse.org#1392433</string>
     </void>
    </object>
   </void>
   <void method="put">
    <string>uk.org.secondfiddle.pep.performance</string>
    <object class="java.util.ArrayList">
     <void method="add">
      <string>http://marketplace.eclipse.org#2117702</string>
     </void>
    </object>
   </void>
  </void>
  <void property="nodeKeyToIU">
   <void method="put">
    <string>http://marketplace.eclipse.org#1277887</string>
    <object class="java.util.ArrayList">
     <void method="add">
      <string>net.atos.webtools.tapestry</string>
     </void>
    </object>
   </void>
   <void method="put">
    <string>http://marketplace.eclipse.org#1504109</string>
    <object class="java.util.ArrayList">
     <void method="add">
      <string>hu.textualmodeler.feature</string>
     </void>
    </object>
   </void>
   <void method="put">
    <string>http://marketplace.eclipse.org#3155121</string>
    <object class="java.util.ArrayList">
     <void method="add">
      <string>com.sap.core.tools.eclipse.server.feature</string>
     </void>
     <void method="add">
      <string>com.sap.core.tools.eclipse.help.feature</string>
     </void>
    </object>
   </void>
   <void method="put">
    <string>http://marketplace.eclipse.org#2117702</string>
    <object class="java.util.ArrayList">
     <void method="add">
      <string>uk.org.secondfiddle.pep</string>
     </void>
     <void method="add">
      <string>uk.org.secondfiddle.pep.pde</string>
     </void>
     <void method="add">
      <string>uk.org.secondfiddle.pep.performance</string>
     </void>
     <void method="add">
      <string>uk.org.secondfiddle.pep.productivity</string>
     </void>
    </object>
   </void>
   <void method="put">
    <string>http://marketplace.eclipse.org#1508744</string>
    <object class="java.util.ArrayList">
     <void method="add">
      <string>org.eclipse.pde.visualization.dependency_feature.feature.group</string>
     </void>
    </object>
   </void>
   <void method="put">
    <string>http://marketplace.eclipse.org#2563246</string>
    <object class="java.util.ArrayList">
     <void method="add">
      <string>com.so.eclipse.helper</string>
     </void>
    </object>
   </void>
   <void method="put">
    <string>http://marketplace.eclipse.org#367947</string>
    <object class="java.util.ArrayList">
     <void method="add">
      <string>net.jeeeyul.pdetools.feature</string>
     </void>
     <void method="add">
      <string>net.jeeeyul.swtend.feature</string>
     </void>
    </object>
   </void>
   <void method="put">
    <string>http://marketplace.eclipse.org#28523</string>
    <object class="java.util.ArrayList">
     <void method="add">
      <string>com.teamunify.eclipse.mylyn.pivotaltracker</string>
     </void>
    </object>
   </void>
   <void method="put">
    <string>http://marketplace.eclipse.org#1465503</string>
    <object class="java.util.ArrayList">
     <void method="add">
      <string>io.sloeber.feature.feature.group</string>
     </void>
    </object>
   </void>
   <void method="put">
    <string>http://marketplace.eclipse.org#2449032</string>
    <object class="java.util.ArrayList">
     <void method="add">
      <string>com.zeroc.IceBuilder</string>
     </void>
    </object>
   </void>
   <void method="put">
    <string>http://marketplace.eclipse.org#539811</string>
    <object class="java.util.ArrayList">
     <void method="add">
      <string>com.github.eclipse.projectlocationupdater.feature</string>
     </void>
    </object>
   </void>
   <void method="put">
    <string>http://marketplace.eclipse.org#29591</string>
    <object class="java.util.ArrayList">
     <void method="add">
      <string>org.zeroturnaround.eclipse.feature</string>
     </void>
     <void method="add">
      <string>org.zeroturnaround.eclipse.wtp.feature</string>
     </void>
     <void method="add">
      <string>org.zeroturnaround.eclipse.m2e.feature</string>
     </void>
    </object>
   </void>
   <void method="put">
    <string>http://marketplace.eclipse.org#3035880</string>
    <object class="java.util.ArrayList">
     <void method="add">
      <string>org.cohorte.eclipse</string>
     </void>
    </object>
   </void>
   <void method="put">
    <string>http://marketplace.eclipse.org#2637354</string>
    <object class="java.util.ArrayList">
     <void method="add">
      <string>io.sloeber.feature.feature.group</string>
     </void>
    </object>
   </void>
   <void method="put">
    <string>http://marketplace.eclipse.org#22937</string>
    <object class="java.util.ArrayList">
     <void method="add">
      <string>com.remainsoftware.featureexplorer.feature</string>
     </void>
    </object>
   </void>
   <void method="put">
    <string>http://marketplace.eclipse.org#1392433</string>
    <object class="java.util.ArrayList">
     <void method="add">
      <string>org.eclipse.jdt.java8patch</string>
     </void>
     <void method="add">
      <string>org.eclipse.pde.java8patch</string>
     </void>
     <void method="add">
      <string>org.eclipse.rcp.java8patch</string>
     </void>
    </object>
   </void>
   <void method="put">
    <string>http://marketplace.eclipse.org#3680354</string>
    <object class="java.util.ArrayList">
     <void method="add">
      <string>de.jcup.jenkinseditor.feature</string>
     </void>
    </object>
   </void>
   <void method="put">
    <string>http://marketplace.eclipse.org#515053</string>
    <object class="java.util.ArrayList">
     <void method="add">
      <string>org.modelbus.core</string>
     </void>
     <void method="add">
      <string>org.modelbus.library.example</string>
     </void>
     <void method="add">
      <string>org.modelbus.papyrus.eclipse.adapter</string>
     </void>
     <void method="add">
      <string>org.modelbus.papyrus.v9.eclipse.adapter</string>
     </void>
     <void method="add">
      <string>org.modelbus.team.eclipse.changemodelnotification</string>
     </void>
     <void method="add">
      <string>org.modelbus.team.eclipse.ui.services</string>
     </void>
     <void method="add">
      <string>org.modelbus.teamprovider.emf.compare11.extension</string>
     </void>
     <void method="add">
      <string>org.modelbus.teamprovider</string>
     </void>
    </object>
   </void>
   <void method="put">
    <string>http://marketplace.eclipse.org#2844330</string>
    <object class="java.util.ArrayList">
     <void method="add">
      <string>org.jboss.tools.pde.sourcelookup.feature</string>
     </void>
    </object>
   </void>
   <void method="put">
    <string>http://marketplace.eclipse.org#2234530</string>
    <object class="java.util.ArrayList">
     <void method="add">
      <string>org.eclipse.pde</string>
     </void>
    </object>
   </void>
   <void method="put">
    <string>http://marketplace.eclipse.org#1023</string>
    <object class="java.util.ArrayList">
     <void method="add">
      <string>com.vaadin.integration.eclipse</string>
     </void>
     <void method="add">
      <string>com.vaadin.designer2.eclipse</string>
     </void>
     <void method="add">
      <string>com.vaadin.designer.eclipse</string>
     </void>
    </object>
   </void>
   <void method="put">
    <string>http://marketplace.eclipse.org#3429028</string>
    <object class="java.util.ArrayList">
     <void method="add">
      <string>com.reprezen.swagedit.feature</string>
     </void>
    </object>
   </void>
  </void>
 </object>
</java>
